.gitignore
.pre-commit-config.yaml
LICENSE
README.md
config_example.yml
pyproject.toml
setup.cfg
.github/workflows/pre-commit.yml
.github/workflows/publish.yml
src/ib2influx/__init__.py
src/ib2influx/loader.py
src/ib2influx/main.py
src/ib2influx/opa.py
src/ib2influx/utils.py
src/ib2influx.egg-info/PKG-INFO
src/ib2influx.egg-info/SOURCES.txt
src/ib2influx.egg-info/dependency_links.txt
src/ib2influx.egg-info/entry_points.txt
src/ib2influx.egg-info/requires.txt
src/ib2influx.egg-info/top_level.txt